setup.py
tanzil_transreader/__init__.py
tanzil_transreader/models.py
tanzil_transreader.egg-info/PKG-INFO
tanzil_transreader.egg-info/SOURCES.txt
tanzil_transreader.egg-info/dependency_links.txt
tanzil_transreader.egg-info/top_level.txt
tanzil_transreader.egg-info/zip-safe